{
    "PressureRange":  [
                          {
                              "Brand":  "XPPEN",
                              "PenEntityId":  "xppen.pen.pd51",
                              "PenInventoryId":  "XPP.0012",
                              "Metric":  "IAF",
                              "Value":  "4.5",
                              "Date":  "2026-06-18",
                              "TabletEntityId":  "xppen.tablet.mt0962b",
                              "TabletInventoryId":  "XPT.0006",
                              "Driver":  "OPENTABLETDRIVER",
                              "OS":  "WINDOWS",
                              "Method":  "",
                              "_id":  "0669f181-c70f-441d-b0d7-5e45b25af68a",
                              "_CreateDate":  "2026-06-18T00:00:00.000Z",
                              "_ModifiedDate":  "2026-06-20T17:30:09.000Z"
                          },
                          {
                              "Brand":  "XPPEN",
                              "PenEntityId":  "xppen.pen.pd04b",
                              "PenInventoryId":  "XPP.0016",
                              "Metric":  "IAF",
                              "Value":  "2.5",
                              "Date":  "2026-06-18",
                              "TabletEntityId":  "xppen.tablet.mt0962b",
                              "TabletInventoryId":  "XPT.0006",
                              "Driver":  "OPENTABLETDRIVER",
                              "OS":  "WINDOWS",
                              "Method":  "",
                              "_id":  "64b85945-908e-4124-8e94-9f3405232343",
                              "_CreateDate":  "2026-06-18T00:00:00.000Z",
                              "_ModifiedDate":  "2026-06-20T17:30:09.000Z"
                          },
                          {
                              "Brand":  "XPPEN",
                              "PenEntityId":  "xppen.pen.pd21",
                              "PenInventoryId":  "XPP.0003",
                              "Metric":  "IAF",
                              "Value":  "10",
                              "Date":  "2026-06-18",
                              "TabletEntityId":  "xppen.tablet.mt0962b",
                              "TabletInventoryId":  "XPT.0006",
                              "Driver":  "OPENTABLETDRIVER",
                              "OS":  "WINDOWS",
                              "Method":  "",
                              "_id":  "1a774876-8811-4b4d-b9d9-2918f8ebe850",
                              "_CreateDate":  "2026-06-18T00:00:00.000Z",
                              "_ModifiedDate":  "2026-06-20T17:30:09.000Z"
                          },
                          {
                              "Brand":  "XPPEN",
                              "PenEntityId":  "xppen.pen.pd21",
                              "PenInventoryId":  "XPP.0002",
                              "Metric":  "IAF",
                              "Value":  "4.5",
                              "Date":  "2026-06-18",
                              "TabletEntityId":  "xppen.tablet.mt0962b",
                              "TabletInventoryId":  "XPT.0006",
                              "Driver":  "OPENTABLETDRIVER",
                              "OS":  "WINDOWS",
                              "Method":  "",
                              "_id":  "dc378e87-d0c6-4187-bf93-d0e84fcca9f6",
                              "_CreateDate":  "2026-06-18T00:00:00.000Z",
                              "_ModifiedDate":  "2026-06-20T17:30:09.000Z"
                          },
                          {
                              "Brand":  "XPPEN",
                              "PenEntityId":  "xppen.pen.pd51",
                              "PenInventoryId":  "XPP.0014",
                              "Metric":  "IAF",
                              "Value":  "4.5",
                              "Date":  "2026-06-18",
                              "TabletEntityId":  "xppen.tablet.mt0962b",
                              "TabletInventoryId":  "XPT.0006",
                              "Driver":  "OPENTABLETDRIVER",
                              "OS":  "WINDOWS",
                              "Method":  "",
                              "_id":  "c206ecfa-d478-424e-a645-7a7480f0492b",
                              "_CreateDate":  "2026-06-18T00:00:00.000Z",
                              "_ModifiedDate":  "2026-06-20T17:30:09.000Z"
                          },
                          {
                              "Brand":  "XPPEN",
                              "PenEntityId":  "xppen.pen.pd51",
                              "PenInventoryId":  "XPP.0019",
                              "Metric":  "IAF",
                              "Value":  "6",
                              "Date":  "2026-06-18",
                              "TabletEntityId":  "xppen.tablet.mt0962b",
                              "TabletInventoryId":  "XPT.0006",
                              "Driver":  "OPENTABLETDRIVER",
                              "OS":  "WINDOWS",
                              "Method":  "",
                              "_id":  "80631e15-6207-46b4-8f64-0e3f28a75f1a",
                              "_CreateDate":  "2026-06-18T00:00:00.000Z",
                              "_ModifiedDate":  "2026-06-20T17:30:09.000Z"
                          },
                          {
                              "Brand":  "XPPEN",
                              "PenEntityId":  "xppen.pen.pd21",
                              "PenInventoryId":  "XPP.0015",
                              "Metric":  "IAF",
                              "Value":  "6",
                              "Date":  "2026-06-18",
                              "TabletEntityId":  "xppen.tablet.mt0962b",
                              "TabletInventoryId":  "XPT.0006",
                              "Driver":  "OPENTABLETDRIVER",
                              "OS":  "WINDOWS",
                              "Method":  "",
                              "_id":  "8fd31717-0aeb-46e1-b64b-fbb6655b11d1",
                              "_CreateDate":  "2026-06-18T00:00:00.000Z",
                              "_ModifiedDate":  "2026-06-20T17:30:09.000Z"
                          },
                          {
                              "Brand":  "XPPEN",
                              "PenEntityId":  "xppen.pen.pd21",
                              "PenInventoryId":  "XPP.0017",
                              "Metric":  "IAF",
                              "Value":  "8.5",
                              "Date":  "2026-06-18",
                              "TabletEntityId":  "xppen.tablet.mt0962b",
                              "TabletInventoryId":  "XPT.0006",
                              "Driver":  "OPENTABLETDRIVER",
                              "OS":  "WINDOWS",
                              "Method":  "",
                              "_id":  "9991c112-3389-406a-80e9-324207127909",
                              "_CreateDate":  "2026-06-18T00:00:00.000Z",
                              "_ModifiedDate":  "2026-06-20T17:30:09.000Z"
                          },
                          {
                              "Brand":  "XPPEN",
                              "PenEntityId":  "xppen.pen.pd51",
                              "PenInventoryId":  "XPP.0008",
                              "Metric":  "IAF",
                              "Value":  "4.5",
                              "Date":  "2026-06-18",
                              "TabletEntityId":  "xppen.tablet.mt0962b",
                              "TabletInventoryId":  "XPT.0006",
                              "Driver":  "OPENTABLETDRIVER",
                              "OS":  "WINDOWS",
                              "Method":  "",
                              "_id":  "ba90cff9-7750-4563-8012-fcc4e9b461b0",
                              "_CreateDate":  "2026-06-18T00:00:00.000Z",
                              "_ModifiedDate":  "2026-06-20T17:30:09.000Z"
                          },
                          {
                              "Brand":  "XPPEN",
                              "PenEntityId":  "xppen.pen.pd22",
                              "PenInventoryId":  "XPP.0007",
                              "Metric":  "IAF",
                              "Value":  "3.5",
                              "Date":  "2026-06-18",
                              "TabletEntityId":  "xppen.tablet.mt0962b",
                              "TabletInventoryId":  "XPT.0006",
                              "Driver":  "OPENTABLETDRIVER",
                              "OS":  "WINDOWS",
                              "Method":  "",
                              "_id":  "9cf35a59-7ad5-46fe-80d3-01fcbffeee4d",
                              "_CreateDate":  "2026-06-18T00:00:00.000Z",
                              "_ModifiedDate":  "2026-06-20T17:30:09.000Z"
                          },
                          {
                              "Brand":  "XPPEN",
                              "PenEntityId":  "xppen.pen.pd21",
                              "PenInventoryId":  "XPP.0001",
                              "Metric":  "IAF",
                              "Value":  "7.5",
                              "Date":  "2026-06-18",
                              "TabletEntityId":  "xppen.tablet.mt0962b",
                              "TabletInventoryId":  "XPT.0006",
                              "Driver":  "OPENTABLETDRIVER",
                              "OS":  "WINDOWS",
                              "Method":  "",
                              "_id":  "c1e2c9da-a07e-4e16-a567-de2c25d85a8d",
                              "_CreateDate":  "2026-06-18T00:00:00.000Z",
                              "_ModifiedDate":  "2026-06-20T17:30:09.000Z"
                          },
                          {
                              "Brand":  "XPPEN",
                              "PenEntityId":  "xppen.pen.pd21",
                              "PenInventoryId":  "XPP.0013",
                              "Metric":  "IAF",
                              "Value":  "4.5",
                              "Date":  "2026-06-18",
                              "TabletEntityId":  "xppen.tablet.mt0962b",
                              "TabletInventoryId":  "XPT.0006",
                              "Driver":  "OPENTABLETDRIVER",
                              "OS":  "WINDOWS",
                              "Method":  "",
                              "_id":  "260fcf82-005e-47c0-81e0-44c064fd90a4",
                              "_CreateDate":  "2026-06-18T00:00:00.000Z",
                              "_ModifiedDate":  "2026-06-20T17:30:09.000Z"
                          },
                          {
                              "Brand":  "XPPEN",
                              "PenEntityId":  "xppen.pen.p05",
                              "PenInventoryId":  "XPP.0005",
                              "Metric":  "IAF",
                              "Value":  "9",
                              "Date":  "2026-06-20",
                              "TabletEntityId":  "xppen.tablet.deco01v3",
                              "TabletInventoryId":  "XPT.0014",
                              "Driver":  "OPENTABLETDRIVER",
                              "OS":  "WINDOWS",
                              "Method":  "",
                              "_id":  "b87dd97b-e01f-4903-af96-df0729ccfcdb",
                              "_CreateDate":  "2026-06-20T00:00:00.000Z",
                              "_ModifiedDate":  "2026-06-20T17:34:40.825Z"
                          },
                          {
                              "Brand":  "XPPEN",
                              "PenEntityId":  "xppen.pen.p05",
                              "PenInventoryId":  "XPP.0020",
                              "Metric":  "IAF",
                              "Value":  "6",
                              "Date":  "2026-06-20",
                              "TabletEntityId":  "xppen.tablet.deco01v3",
                              "TabletInventoryId":  "XPT.0014",
                              "Driver":  "OPENTABLETDRIVER",
                              "OS":  "WINDOWS",
                              "Method":  "",
                              "_id":  "f03cab14-89a8-4682-943e-eafcd0715805",
                              "_CreateDate":  "2026-06-20T00:00:00.000Z",
                              "_ModifiedDate":  "2026-06-20T00:00:00.000Z"
                          },
                          {
                              "Brand":  "XPPEN",
                              "PenEntityId":  "xppen.pen.p05",
                              "PenInventoryId":  "XPP.0006",
                              "Metric":  "IAF",
                              "Value":  "6.5",
                              "Date":  "2026-06-20",
                              "TabletEntityId":  "xppen.tablet.deco01v3",
                              "TabletInventoryId":  "XPT.0014",
                              "Driver":  "OPENTABLETDRIVER",
                              "OS":  "WINDOWS",
                              "Method":  "",
                              "_id":  "1e912f81-70fc-4776-91dc-1a1e9af713c7",
                              "_CreateDate":  "2026-06-20T00:00:00.000Z",
                              "_ModifiedDate":  "2026-06-20T00:00:00.000Z"
                          },
                          {
                              "Brand":  "XPPEN",
                              "PenEntityId":  "xppen.pen.p05",
                              "PenInventoryId":  "XPP.0004",
                              "Metric":  "IAF",
                              "Value":  "7.5",
                              "Date":  "2026-06-20",
                              "TabletEntityId":  "xppen.tablet.deco01v3",
                              "TabletInventoryId":  "XPT.0014",
                              "Driver":  "OPENTABLETDRIVER",
                              "OS":  "WINDOWS",
                              "Method":  "",
                              "_id":  "f87196e4-599e-4904-b2a7-9e2b28d4b030",
                              "_CreateDate":  "2026-06-20T00:00:00.000Z",
                              "_ModifiedDate":  "2026-06-20T00:00:00.000Z"
                          },
                          {
                              "Brand":  "XPPEN",
                              "PenEntityId":  "xppen.pen.ph10b",
                              "PenInventoryId":  "XPP.0011",
                              "Metric":  "IAF",
                              "Value":  "6",
                              "Date":  "2026-06-20",
                              "TabletEntityId":  "xppen.tablet.cd130fh",
                              "TabletInventoryId":  "XPT.0002",
                              "Driver":  "XPPEN",
                              "OS":  "WINDOWS",
                              "Method":  "",
                              "_id":  "bbb5b731-8473-4584-b11d-66643d270c33",
                              "_CreateDate":  "2026-06-20T00:00:00.000Z",
                              "_ModifiedDate":  "2026-06-20T00:00:00.000Z"
                          },
                          {
                              "Brand":  "XPPEN",
                              "PenEntityId":  "xppen.pen.ph10b",
                              "PenInventoryId":  "XPP.0018",
                              "Metric":  "IAF",
                              "Value":  "3.7",
                              "Date":  "2026-06-20",
                              "TabletEntityId":  "xppen.tablet.cd130fh",
                              "TabletInventoryId":  "XPT.0002",
                              "Driver":  "XPPEN",
                              "OS":  "WINDOWS",
                              "Method":  "",
                              "_id":  "25abd852-7a32-4fe7-9dfe-f852a6918271",
                              "_CreateDate":  "2026-06-20T00:00:00.000Z",
                              "_ModifiedDate":  "2026-06-20T00:00:00.000Z"
                          },
                          {
                              "Brand":  "XPPEN",
                              "PenEntityId":  "xppen.pen.ph10b",
                              "PenInventoryId":  "XPP.0010",
                              "Metric":  "IAF",
                              "Value":  "4.5",
                              "Date":  "2026-06-20",
                              "TabletEntityId":  "xppen.tablet.cd130fh",
                              "TabletInventoryId":  "XPT.0002",
                              "Driver":  "XPPEN",
                              "OS":  "WINDOWS",
                              "Method":  "",
                              "_id":  "ca116f1d-793c-47f0-a9e6-2824b1e16c72",
                              "_CreateDate":  "2026-06-20T00:00:00.000Z",
                              "_ModifiedDate":  "2026-06-20T00:00:00.000Z"
                          },
                          {
                              "Brand":  "XPPEN",
                              "PenEntityId":  "xppen.pen.ph10b",
                              "PenInventoryId":  "XPP.0009",
                              "Metric":  "IAF",
                              "Value":  "9.75",
                              "Date":  "2026-06-20",
                              "TabletEntityId":  "xppen.tablet.cd130fh",
                              "TabletInventoryId":  "XPT.0002",
                              "Driver":  "XPPEN",
                              "OS":  "WINDOWS",
                              "Method":  "",
                              "_id":  "d0aa6325-0e99-4b75-8bcd-0bec4c115166",
                              "_CreateDate":  "2026-06-20T00:00:00.000Z",
                              "_ModifiedDate":  "2026-06-20T00:00:00.000Z"
                          },
                          {
                              "Brand":  "XPPEN",
                              "PenEntityId":  "xppen.pen.p05",
                              "PenInventoryId":  "XPP.0004",
                              "Metric":  "IAF",
                              "Value":  "7",
                              "Date":  "2024-10-01",
                              "TabletEntityId":  "xppen.tablet.deco01v2",
                              "Driver":  "XPPEN",
                              "OS":  "WINDOWS",
                              "Method":  "",
                              "_id":  "f5c7e97e-0bba-4000-8177-5e171699994b",
                              "_CreateDate":  "2026-06-25T00:00:00.000Z",
                              "_ModifiedDate":  "2026-06-25T00:00:00.000Z"
                          },
                          {
                              "Brand":  "XPPEN",
                              "PenEntityId":  "xppen.pen.p05",
                              "PenInventoryId":  "XPP.0004",
                              "Metric":  "IAF",
                              "Value":  "7",
                              "Date":  "2025-09-24",
                              "TabletEntityId":  "xppen.tablet.deco01v3",
                              "Driver":  "XPPEN",
                              "OS":  "WINDOWS",
                              "Method":  "",
                              "_id":  "6f5c0405-7c5d-4fd9-b931-9b0bcb5030a3",
                              "_CreateDate":  "2026-06-25T00:00:00.000Z",
                              "_ModifiedDate":  "2026-06-25T00:00:00.000Z"
                          },
                          {
                              "Brand":  "XPPEN",
                              "PenEntityId":  "xppen.pen.p05",
                              "PenInventoryId":  "XPP.0005",
                              "Metric":  "IAF",
                              "Value":  "7.2",
                              "Date":  "2024-10-01",
                              "TabletEntityId":  "xppen.tablet.deco01v2",
                              "Driver":  "XPPEN",
                              "OS":  "WINDOWS",
                              "Method":  "",
                              "_id":  "43416b9b-56cc-452a-ab68-3b1609dce32d",
                              "_CreateDate":  "2026-06-25T00:00:00.000Z",
                              "_ModifiedDate":  "2026-06-25T00:00:00.000Z"
                          },
                          {
                              "Brand":  "XPPEN",
                              "PenEntityId":  "xppen.pen.p05",
                              "PenInventoryId":  "XPP.0005",
                              "Metric":  "IAF",
                              "Value":  "8.5",
                              "Date":  "2025-09-24",
                              "TabletEntityId":  "xppen.tablet.deco01v3",
                              "Driver":  "XPPEN",
                              "OS":  "WINDOWS",
                              "Method":  "",
                              "_id":  "f8420d97-1ea4-4477-b4fb-3a036bd014e9",
                              "_CreateDate":  "2026-06-25T00:00:00.000Z",
                              "_ModifiedDate":  "2026-06-25T00:00:00.000Z"
                          },
                          {
                              "Brand":  "XPPEN",
                              "PenEntityId":  "xppen.pen.p05",
                              "PenInventoryId":  "XPP.0006",
                              "Metric":  "IAF",
                              "Value":  "6.1",
                              "Date":  "2024-10-01",
                              "TabletEntityId":  "xppen.tablet.deco01v2",
                              "Driver":  "XPPEN",
                              "OS":  "WINDOWS",
                              "Method":  "",
                              "_id":  "862a4060-e2e4-4fba-9666-d2b30b2d2bcb",
                              "_CreateDate":  "2026-06-25T00:00:00.000Z",
                              "_ModifiedDate":  "2026-06-25T00:00:00.000Z"
                          },
                          {
                              "Brand":  "XPPEN",
                              "PenEntityId":  "xppen.pen.p05",
                              "PenInventoryId":  "XPP.0006",
                              "Metric":  "IAF",
                              "Value":  "6.5",
                              "Date":  "2025-09-24",
                              "TabletEntityId":  "xppen.tablet.deco01v3",
                              "Driver":  "XPPEN",
                              "OS":  "WINDOWS",
                              "Method":  "",
                              "_id":  "4d4b3c3b-59c0-4d22-8fbd-07825e48566e",
                              "_CreateDate":  "2026-06-25T00:00:00.000Z",
                              "_ModifiedDate":  "2026-06-25T00:00:00.000Z"
                          },
                          {
                              "Brand":  "XPPEN",
                              "PenEntityId":  "xppen.pen.p05",
                              "PenInventoryId":  "XPP.0020",
                              "Metric":  "IAF",
                              "Value":  "6.1",
                              "Date":  "2025-09-24",
                              "TabletEntityId":  "xppen.tablet.deco01v3",
                              "Driver":  "XPPEN",
                              "OS":  "WINDOWS",
                              "Method":  "",
                              "_id":  "4702c022-0ab3-47bf-9fe9-cc8290e4c9bd",
                              "_CreateDate":  "2026-06-25T00:00:00.000Z",
                              "_ModifiedDate":  "2026-06-25T00:00:00.000Z"
                          },
                          {
                              "Brand":  "XPPEN",
                              "PenEntityId":  "xppen.pen.ph10b",
                              "PenInventoryId":  "XPP.0009",
                              "Metric":  "IAF",
                              "Value":  "6.3",
                              "Date":  "2024-09-26",
                              "TabletEntityId":  "xppen.tablet.it1060b",
                              "Driver":  "XPPEN",
                              "OS":  "WINDOWS",
                              "Method":  "",
                              "_id":  "e5a92350-3784-4d9c-bb07-54a07dd47f45",
                              "_CreateDate":  "2026-06-25T00:00:00.000Z",
                              "_ModifiedDate":  "2026-06-25T00:00:00.000Z"
                          },
                          {
                              "Brand":  "XPPEN",
                              "PenEntityId":  "xppen.pen.ph10b",
                              "PenInventoryId":  "XPP.0010",
                              "Metric":  "IAF",
                              "Value":  "4.2",
                              "Date":  "2024-09-27",
                              "TabletEntityId":  "xppen.tablet.it1060b",
                              "Driver":  "XPPEN",
                              "OS":  "WINDOWS",
                              "Method":  "",
                              "_id":  "ef5b548c-b677-4990-bc52-6ae203d3b4fc",
                              "_CreateDate":  "2026-06-25T00:00:00.000Z",
                              "_ModifiedDate":  "2026-06-25T00:00:00.000Z"
                          },
                          {
                              "Brand":  "XPPEN",
                              "PenEntityId":  "xppen.pen.ph10b",
                              "PenInventoryId":  "XPP.0010",
                              "Metric":  "IAF",
                              "Value":  "3.6",
                              "Date":  "2025-09-25",
                              "TabletEntityId":  "xppen.tablet.it850b",
                              "Driver":  "XPPEN",
                              "OS":  "WINDOWS",
                              "Method":  "",
                              "_id":  "8de4e042-b07f-4a01-890a-6c193a11abd0",
                              "_CreateDate":  "2026-06-25T00:00:00.000Z",
                              "_ModifiedDate":  "2026-06-25T00:00:00.000Z"
                          },
                          {
                              "Brand":  "XPPEN",
                              "PenEntityId":  "xppen.pen.ph10b",
                              "PenInventoryId":  "XPP.0011",
                              "Metric":  "IAF",
                              "Value":  "5.9",
                              "Date":  "2024-09-27",
                              "TabletEntityId":  "xppen.tablet.it1060b",
                              "Driver":  "XPPEN",
                              "OS":  "WINDOWS",
                              "Method":  "",
                              "_id":  "9506aaae-ed42-4839-af34-a0597da62aff",
                              "_CreateDate":  "2026-06-25T00:00:00.000Z",
                              "_ModifiedDate":  "2026-06-25T00:00:00.000Z"
                          },
                          {
                              "Brand":  "XPPEN",
                              "PenEntityId":  "xppen.pen.ph10b",
                              "PenInventoryId":  "XPP.0011",
                              "Metric":  "IAF",
                              "Value":  "6.1",
                              "Date":  "2025-09-25",
                              "TabletEntityId":  "xppen.tablet.it850b",
                              "Driver":  "XPPEN",
                              "OS":  "WINDOWS",
                              "Method":  "",
                              "_id":  "d6009357-7115-42ed-857f-244f265e62c1",
                              "_CreateDate":  "2026-06-25T00:00:00.000Z",
                              "_ModifiedDate":  "2026-06-25T00:00:00.000Z"
                          },
                          {
                              "Brand":  "XPPEN",
                              "PenEntityId":  "xppen.pen.ph10b",
                              "PenInventoryId":  "XPP.0018",
                              "Metric":  "IAF",
                              "Value":  "3.7",
                              "Date":  "2025-09-25",
                              "TabletEntityId":  "xppen.tablet.it850b",
                              "Driver":  "XPPEN",
                              "OS":  "WINDOWS",
                              "Method":  "",
                              "_id":  "c527ffec-8c63-4706-ba7c-176ce147bf42",
                              "_CreateDate":  "2026-06-25T00:00:00.000Z",
                              "_ModifiedDate":  "2026-06-25T00:00:00.000Z"
                          },
                          {
                              "Brand":  "XPPEN",
                              "PenEntityId":  "xppen.pen.ph10b",
                              "PenInventoryId":  "XPP.0009",
                              "Metric":  "IAF",
                              "Value":  "8.8",
                              "Date":  "2025-09-25",
                              "TabletEntityId":  "xppen.tablet.it850b",
                              "Driver":  "XPPEN",
                              "OS":  "WINDOWS",
                              "Method":  "",
                              "_id":  "8fd4bdca-219d-4942-ab8d-8428602b2092",
                              "_CreateDate":  "2026-06-25T00:00:00.000Z",
                              "_ModifiedDate":  "2026-06-25T00:00:00.000Z"
                          },
                          {
                              "Brand":  "XPPEN",
                              "PenEntityId":  "xppen.pen.pd21",
                              "PenInventoryId":  "XPP.0001",
                              "Metric":  "IAF",
                              "Value":  "3.7",
                              "Date":  "2024-09-26",
                              "TabletEntityId":  "xppen.tablet.mt1592b",
                              "Driver":  "XPPEN",
                              "OS":  "WINDOWS",
                              "Method":  "",
                              "_id":  "fe2aaee7-d37f-44da-80e2-134e2eb4c6fa",
                              "_CreateDate":  "2026-06-25T00:00:00.000Z",
                              "_ModifiedDate":  "2026-06-25T00:00:00.000Z"
                          },
                          {
                              "Brand":  "XPPEN",
                              "PenEntityId":  "xppen.pen.pd21",
                              "PenInventoryId":  "XPP.0001",
                              "Metric":  "IAF",
                              "Value":  "2.8",
                              "Date":  "2025-09-25",
                              "TabletEntityId":  "xppen.tablet.mt0962b",
                              "Driver":  "XPPEN",
                              "OS":  "WINDOWS",
                              "Method":  "",
                              "_id":  "d5b1f5d7-626c-4ebd-8e5e-611ad0443ffc",
                              "_CreateDate":  "2026-06-25T00:00:00.000Z",
                              "_ModifiedDate":  "2026-06-25T00:00:00.000Z"
                          },
                          {
                              "Brand":  "XPPEN",
                              "PenEntityId":  "xppen.pen.pd21",
                              "PenInventoryId":  "XPP.0002",
                              "Metric":  "IAF",
                              "Value":  "2.3",
                              "Date":  "2024-09-25",
                              "TabletEntityId":  "xppen.tablet.mt1592b",
                              "Driver":  "XPPEN",
                              "OS":  "WINDOWS",
                              "Method":  "",
                              "_id":  "5d4fbcbb-bd56-4679-8de6-16c914f93ed6",
                              "_CreateDate":  "2026-06-25T00:00:00.000Z",
                              "_ModifiedDate":  "2026-06-25T00:00:00.000Z"
                          },
                          {
                              "Brand":  "XPPEN",
                              "PenEntityId":  "xppen.pen.pd21",
                              "PenInventoryId":  "XPP.0002",
                              "Metric":  "IAF",
                              "Value":  "2.5",
                              "Date":  "2025-09-25",
                              "TabletEntityId":  "xppen.tablet.mt0962b",
                              "Driver":  "XPPEN",
                              "OS":  "WINDOWS",
                              "Method":  "",
                              "_id":  "3be50291-7b12-4b0a-bd8f-c99561556a73",
                              "_CreateDate":  "2026-06-25T00:00:00.000Z",
                              "_ModifiedDate":  "2026-06-25T00:00:00.000Z"
                          },
                          {
                              "Brand":  "XPPEN",
                              "PenEntityId":  "xppen.pen.pd21",
                              "PenInventoryId":  "XPP.0003",
                              "Metric":  "IAF",
                              "Value":  "5.8",
                              "Date":  "2024-09-26",
                              "TabletEntityId":  "xppen.tablet.mt1592b",
                              "Driver":  "XPPEN",
                              "OS":  "WINDOWS",
                              "Method":  "",
                              "_id":  "a333c08c-90af-40bd-a849-c91b16c1bec0",
                              "_CreateDate":  "2026-06-25T00:00:00.000Z",
                              "_ModifiedDate":  "2026-06-25T00:00:00.000Z"
                          },
                          {
                              "Brand":  "XPPEN",
                              "PenEntityId":  "xppen.pen.pd21",
                              "PenInventoryId":  "XPP.0003",
                              "Metric":  "IAF",
                              "Value":  "5.3",
                              "Date":  "2025-09-25",
                              "TabletEntityId":  "xppen.tablet.mt0962b",
                              "Driver":  "XPPEN",
                              "OS":  "WINDOWS",
                              "Method":  "",
                              "_id":  "2f575d80-9981-4bc1-abb7-80fb5bd19f94",
                              "_CreateDate":  "2026-06-25T00:00:00.000Z",
                              "_ModifiedDate":  "2026-06-25T00:00:00.000Z"
                          },
                          {
                              "Brand":  "XPPEN",
                              "PenEntityId":  "xppen.pen.pd21",
                              "PenInventoryId":  "XPP.0013",
                              "Metric":  "IAF",
                              "Value":  "2.7",
                              "Date":  "2024-11-01",
                              "TabletEntityId":  "xppen.tablet.mt1592b",
                              "Driver":  "XPPEN",
                              "OS":  "WINDOWS",
                              "Method":  "",
                              "_id":  "f6feeff6-c6dc-4c4b-8494-3399467355b2",
                              "_CreateDate":  "2026-06-25T00:00:00.000Z",
                              "_ModifiedDate":  "2026-06-25T00:00:00.000Z"
                          },
                          {
                              "Brand":  "XPPEN",
                              "PenEntityId":  "xppen.pen.pd21",
                              "PenInventoryId":  "XPP.0013",
                              "Metric":  "IAF",
                              "Value":  "2.9",
                              "Date":  "2025-09-25",
                              "TabletEntityId":  "xppen.tablet.mt0962b",
                              "Driver":  "XPPEN",
                              "OS":  "WINDOWS",
                              "Method":  "",
                              "_id":  "fffedaef-8d23-40a5-a441-a25b0810ea5c",
                              "_CreateDate":  "2026-06-25T00:00:00.000Z",
                              "_ModifiedDate":  "2026-06-25T00:00:00.000Z"
                          },
                          {
                              "Brand":  "XPPEN",
                              "PenEntityId":  "xppen.pen.pd21",
                              "PenInventoryId":  "XPP.0015",
                              "Metric":  "IAF",
                              "Value":  "5",
                              "Date":  "2025-03-25",
                              "TabletEntityId":  "xppen.tablet.mt1592b",
                              "Driver":  "XPPEN",
                              "OS":  "WINDOWS",
                              "Method":  "",
                              "_id":  "6fde4e7f-3a11-4714-9afb-f3040d6c71e6",
                              "_CreateDate":  "2026-06-25T00:00:00.000Z",
                              "_ModifiedDate":  "2026-06-25T00:00:00.000Z"
                          },
                          {
                              "Brand":  "XPPEN",
                              "PenEntityId":  "xppen.pen.pd21",
                              "PenInventoryId":  "XPP.0015",
                              "Metric":  "IAF",
                              "Value":  "3.4",
                              "Date":  "2025-09-25",
                              "TabletEntityId":  "xppen.tablet.mt0962b",
                              "Driver":  "XPPEN",
                              "OS":  "WINDOWS",
                              "Method":  "",
                              "_id":  "dd113e6b-7052-46a6-bf26-4fba4ec37528",
                              "_CreateDate":  "2026-06-25T00:00:00.000Z",
                              "_ModifiedDate":  "2026-06-25T00:00:00.000Z"
                          },
                          {
                              "Brand":  "XPPEN",
                              "PenEntityId":  "xppen.pen.pd21",
                              "PenInventoryId":  "XPP.0017",
                              "Metric":  "IAF",
                              "Value":  "4.7",
                              "Date":  "2025-09-25",
                              "TabletEntityId":  "xppen.tablet.mt0962b",
                              "Driver":  "XPPEN",
                              "OS":  "WINDOWS",
                              "Method":  "",
                              "_id":  "53475584-0cf7-4900-a483-626c956f0ee9",
                              "_CreateDate":  "2026-06-25T00:00:00.000Z",
                              "_ModifiedDate":  "2026-06-25T00:00:00.000Z"
                          },
                          {
                              "Brand":  "XPPEN",
                              "PenEntityId":  "xppen.pen.pd04b",
                              "PenInventoryId":  "XPP.0016",
                              "Metric":  "IAF",
                              "Value":  "1.7",
                              "Date":  "2025-03-25",
                              "TabletEntityId":  "xppen.tablet.mt1592b",
                              "Driver":  "XPPEN",
                              "OS":  "WINDOWS",
                              "Method":  "",
                              "_id":  "87815eb5-ef1b-424a-96fc-6e26f5933569",
                              "_CreateDate":  "2026-06-25T00:00:00.000Z",
                              "_ModifiedDate":  "2026-06-25T00:00:00.000Z"
                          },
                          {
                              "Brand":  "XPPEN",
                              "PenEntityId":  "xppen.pen.pd04b",
                              "PenInventoryId":  "XPP.0016",
                              "Metric":  "IAF",
                              "Value":  "1.5",
                              "Date":  "2025-09-25",
                              "TabletEntityId":  "xppen.tablet.mt0962b",
                              "Driver":  "XPPEN",
                              "OS":  "WINDOWS",
                              "Method":  "",
                              "_id":  "7619b2b4-826f-4811-8f49-1eff83c4c984",
                              "_CreateDate":  "2026-06-25T00:00:00.000Z",
                              "_ModifiedDate":  "2026-06-25T00:00:00.000Z"
                          },
                          {
                              "Brand":  "XPPEN",
                              "PenEntityId":  "xppen.pen.pd22",
                              "PenInventoryId":  "XPP.0007",
                              "Metric":  "IAF",
                              "Value":  "2",
                              "Date":  "2024-09-26",
                              "TabletEntityId":  "xppen.tablet.mt1592b",
                              "Driver":  "XPPEN",
                              "OS":  "WINDOWS",
                              "Method":  "",
                              "_id":  "91b08b9e-93c0-4e07-85ff-9231ac8589c4",
                              "_CreateDate":  "2026-06-25T00:00:00.000Z",
                              "_ModifiedDate":  "2026-06-25T00:00:00.000Z"
                          },
                          {
                              "Brand":  "XPPEN",
                              "PenEntityId":  "xppen.pen.pd22",
                              "PenInventoryId":  "XPP.0007",
                              "Metric":  "IAF",
                              "Value":  "2.5",
                              "Date":  "2025-09-25",
                              "TabletEntityId":  "xppen.tablet.mt0962b",
                              "Driver":  "XPPEN",
                              "OS":  "WINDOWS",
                              "Method":  "",
                              "_id":  "2c77f07f-01d8-40c3-b7b0-544f22deb26b",
                              "_CreateDate":  "2026-06-25T00:00:00.000Z",
                              "_ModifiedDate":  "2026-06-25T00:00:00.000Z"
                          },
                          {
                              "Brand":  "XPPEN",
                              "PenEntityId":  "xppen.pen.pd51",
                              "PenInventoryId":  "XPP.0008",
                              "Metric":  "IAF",
                              "Value":  "2.7",
                              "Date":  "2024-09-26",
                              "TabletEntityId":  "xppen.tablet.mt1592b",
                              "Driver":  "XPPEN",
                              "OS":  "WINDOWS",
                              "Method":  "",
                              "_id":  "690544cb-5340-4b0e-b4c5-527413c88254",
                              "_CreateDate":  "2026-06-25T00:00:00.000Z",
                              "_ModifiedDate":  "2026-06-25T00:00:00.000Z"
                          },
                          {
                              "Brand":  "XPPEN",
                              "PenEntityId":  "xppen.pen.pd51",
                              "PenInventoryId":  "XPP.0008",
                              "Metric":  "IAF",
                              "Value":  "2.7",
                              "Date":  "2025-09-25",
                              "TabletEntityId":  "xppen.tablet.mt0962b",
                              "Driver":  "XPPEN",
                              "OS":  "WINDOWS",
                              "Method":  "",
                              "_id":  "ac4ae1e8-caa3-4db2-8b61-764904642611",
                              "_CreateDate":  "2026-06-25T00:00:00.000Z",
                              "_ModifiedDate":  "2026-06-25T00:00:00.000Z"
                          },
                          {
                              "Brand":  "XPPEN",
                              "PenEntityId":  "xppen.pen.pd51",
                              "PenInventoryId":  "XPP.0012",
                              "Metric":  "IAF",
                              "Value":  "3.2",
                              "Date":  "2024-11-01",
                              "TabletEntityId":  "xppen.tablet.mt1592b",
                              "Driver":  "XPPEN",
                              "OS":  "WINDOWS",
                              "Method":  "",
                              "_id":  "104c3331-5f2e-428f-838d-85785c65f375",
                              "_CreateDate":  "2026-06-25T00:00:00.000Z",
                              "_ModifiedDate":  "2026-06-25T00:00:00.000Z"
                          },
                          {
                              "Brand":  "XPPEN",
                              "PenEntityId":  "xppen.pen.pd51",
                              "PenInventoryId":  "XPP.0012",
                              "Metric":  "IAF",
                              "Value":  "2.9",
                              "Date":  "2025-09-25",
                              "TabletEntityId":  "xppen.tablet.mt0962b",
                              "Driver":  "XPPEN",
                              "OS":  "WINDOWS",
                              "Method":  "",
                              "_id":  "e989e40e-39b5-47eb-b16b-b0d6abbb24df",
                              "_CreateDate":  "2026-06-25T00:00:00.000Z",
                              "_ModifiedDate":  "2026-06-25T00:00:00.000Z"
                          },
                          {
                              "Brand":  "XPPEN",
                              "PenEntityId":  "xppen.pen.pd51",
                              "PenInventoryId":  "XPP.0014",
                              "Metric":  "IAF",
                              "Value":  "2.5",
                              "Date":  "2024-11-01",
                              "TabletEntityId":  "xppen.tablet.mt1592b",
                              "Driver":  "XPPEN",
                              "OS":  "WINDOWS",
                              "Method":  "",
                              "_id":  "8f3ffecd-fda8-4142-b888-1c9e945113bc",
                              "_CreateDate":  "2026-06-25T00:00:00.000Z",
                              "_ModifiedDate":  "2026-06-25T00:00:00.000Z"
                          },
                          {
                              "Brand":  "XPPEN",
                              "PenEntityId":  "xppen.pen.pd51",
                              "PenInventoryId":  "XPP.0014",
                              "Metric":  "IAF",
                              "Value":  "1.9",
                              "Date":  "2025-09-25",
                              "TabletEntityId":  "xppen.tablet.mt0962b",
                              "Driver":  "XPPEN",
                              "OS":  "WINDOWS",
                              "Method":  "",
                              "_id":  "6e9a7f36-1680-413e-a969-b1f8ba633cf2",
                              "_CreateDate":  "2026-06-25T00:00:00.000Z",
                              "_ModifiedDate":  "2026-06-25T00:00:00.000Z"
                          },
                          {
                              "Brand":  "XPPEN",
                              "PenEntityId":  "xppen.pen.pd51",
                              "PenInventoryId":  "XPP.0019",
                              "Metric":  "IAF",
                              "Value":  "2.4",
                              "Date":  "2025-09-25",
                              "TabletEntityId":  "xppen.tablet.mt0962b",
                              "Driver":  "XPPEN",
                              "OS":  "WINDOWS",
                              "Method":  "",
                              "_id":  "7b94d76c-9c85-4466-ae4a-9835c38e83d6",
                              "_CreateDate":  "2026-06-25T00:00:00.000Z",
                              "_ModifiedDate":  "2026-06-25T00:00:00.000Z"
                          }
                      ]
}
